[
  {
    "id": 26,
    "first_name": "Lucas",
    "last_name": "Aranda",
    "email": "lucas1882@gmail.com",
    "password": "$2b$10$VWSbZVi7zZWlA7NPTqJvreXg3FujfR/JZsC.1O8FuZp66qhGdf0Ci",
    "image": "image-1611463695263.png",
    "category": "user"
  },
  {
    "id": 2,
    "first_name": "ale",
    "last_name": "ale",
    "email": "ale1882@gmail.com",
    "password": "$2b$10$7/j7FC0S0KS3S5jwJSYut.uWJXSf3uhWhMz9wliFKThZfCEd8qLwK",
    "image": "image-1611465233014.png",
    "category": "user"
  },
  {
    "id": 3,
    "first_name": "Lucas",
    "last_name": "Aranda",
    "email": "pepe1882@gmail.com",
    "password": "$2b$10$YwtFzptjGpJH8xQnP0QlJO6BA5KMY0v27ESNsEbolRgHJ9f/mrxTm",
    "image": "image-1611467056373.png",
    "category": "admin"
  }
]